uisrnn/__init__.py
uisrnn/arguments.py
uisrnn/evals.py
uisrnn/loss_func.py
uisrnn/uisrnn.py
uisrnn/utils.py
uisrnn/contrib/__init__.py
uisrnn/contrib/contrib_template.py
uisrnn/contrib/range_search_crp_alpha.py
uisrnn-0.1.2.dist-info/LICENSE
uisrnn-0.1.2.dist-info/METADATA
uisrnn-0.1.2.dist-info/WHEEL
uisrnn-0.1.2.dist-info/top_level.txt
uisrnn-0.1.2.dist-info/RECORD
