Metadata-Version: 2.1
Name: uisrnn
Version: 0.1.2
Summary: Unbounded Interleaved-State Recurrent Neural Network
Home-page: https://github.com/google/uis-rnn
Author: Quan Wang
Author-email: quanw@google.com
Classifier: Programming Language :: Python :: 3
Classifier: License :: OSI Approved :: Apache Software License
Classifier: Operating System :: OS Independent
License-File: LICENSE
Requires-Dist: numpy>=1.18.0
Requires-Dist: scipy>=1.1.0
Requires-Dist: torch>=1.4.0
Requires-Dist: codecov==2.1.13
Requires-Dist: coverage==7.6.0
Requires-Dist: colortimelog
